hydrascreen/__init__.py
hydrascreen/api.py
hydrascreen/predictor.py
hydrascreen-0.0.8.dist-info/LICENSE.txt
hydrascreen-0.0.8.dist-info/METADATA
hydrascreen-0.0.8.dist-info/WHEEL
hydrascreen-0.0.8.dist-info/top_level.txt
hydrascreen-0.0.8.dist-info/RECORD
