Metadata-Version: 2.1
Name: hydrascreen
Version: 0.0.8
Summary: Hydrascreen Python package.
Author: Ro5 Inc.
Author-email: support@ro5.ai
License: Non-commercial
Project-URL: Source, https://github.com/Ro5-ai/hydrascreen
Project-URL: Medium, https://medium.com/@ro5.ai
Classifier: Programming Language :: Python :: 3.9
Classifier: Programming Language :: Python :: 3.10
Classifier: Programming Language :: Python :: 3.11
Classifier: Operating System :: OS Independent
Requires-Python: >=3.9
License-File: LICENSE.txt
Requires-Dist: pandas <3,>=2.0.2
Requires-Dist: requests <3,>=2.31.0
Provides-Extra: dev
Requires-Dist: appengine-python-standard <2,>=1.1.2 ; extra == 'dev'
Requires-Dist: black ==23.3.0 ; extra == 'dev'
Requires-Dist: build ==0.10.0 ; extra == 'dev'
Requires-Dist: bump2version ==1.0.1 ; extra == 'dev'
Requires-Dist: flake8 ==6.0.0 ; extra == 'dev'
Requires-Dist: mypy ==1.4.1 ; extra == 'dev'
Requires-Dist: pip-tools ==6.13.0 ; extra == 'dev'
Requires-Dist: pre-commit ==3.3.3 ; extra == 'dev'
Requires-Dist: pytest ==7.4.0 ; extra == 'dev'
Requires-Dist: setuptools ==68.0.0 ; extra == 'dev'
